decipherment/__init__.py
decipherment/__main__.py
decipherment/add_subtract.py
decipherment/base.py
decipherment/cli.py
decipherment-0.1.2.dist-info/LICENSE
decipherment-0.1.2.dist-info/METADATA
decipherment-0.1.2.dist-info/WHEEL
decipherment-0.1.2.dist-info/entry_points.txt
decipherment-0.1.2.dist-info/top_level.txt
decipherment-0.1.2.dist-info/RECORD
