Metadata-Version: 2.1
Name: decipherment
Version: 0.1.2
Summary: Awesome decipherment created by ivnle
Home-page: https://github.com/ivnle/decipherment/
Author: ivnle
License: UNKNOWN
Platform: UNKNOWN
Provides-Extra: test
Requires-Dist: pytest ; extra == 'test'
Requires-Dist: coverage ; extra == 'test'
Requires-Dist: flake8 ; extra == 'test'
Requires-Dist: black ; extra == 'test'
Requires-Dist: isort ; extra == 'test'
Requires-Dist: pytest-cov ; extra == 'test'
Requires-Dist: codecov ; extra == 'test'
Requires-Dist: mypy ; extra == 'test'
Requires-Dist: gitchangelog ; extra == 'test'
Requires-Dist: mkdocs ; extra == 'test'
